lenses/__init__.py
lenses/const.py
lenses/functorisor.py
lenses/identity.py
lenses/maybe.py
lenses/typeclass.py
lenses/hooks/__init__.py
lenses/hooks/hook_funcs.py
lenses/hooks/pyrsistent.py
lenses/optics/__init__.py
lenses/optics/base.py
lenses/optics/folds.py
lenses/optics/isomorphisms.py
lenses/optics/prisms.py
lenses/optics/setters.py
lenses/optics/traversals.py
lenses/optics/true_lenses.py
lenses/ui/__init__.py
lenses/ui/base.py
lenses/ui/state_func.py
lenses-1.2.0.dist-info/LICENSE
lenses-1.2.0.dist-info/METADATA
lenses-1.2.0.dist-info/WHEEL
lenses-1.2.0.dist-info/top_level.txt
lenses-1.2.0.dist-info/RECORD
