Metadata-Version: 2.1
Name: lenses
Version: 1.2.0
Summary: A lens library for python
Home-page: https://github.com/ingolemo/python-lenses
Author: Adrian Room
Author-email: ingolemo@gmail.com
License: GPLv3+
Keywords: lens lenses immutable functional optics
Classifier: Development Status :: 5 - Production/Stable
Classifier: Intended Audience :: Developers
Classifier: License :: OSI Approved :: GNU General Public License v3 or later (GPLv3+)
Classifier: Natural Language :: English
Classifier: Programming Language :: Python :: 3
Classifier: Programming Language :: Python :: 3.7
Classifier: Programming Language :: Python :: 3.8
Classifier: Programming Language :: Python :: 3.9
Classifier: Programming Language :: Python :: 3.10
Classifier: Programming Language :: Python :: 3.11
Classifier: Programming Language :: Python :: Implementation :: CPython
Classifier: Programming Language :: Python :: Implementation :: PyPy
Classifier: Topic :: Software Development :: Libraries
Requires-Python: >=3.7, <4
License-File: LICENSE
Provides-Extra: docs
Requires-Dist: sphinx ; extra == 'docs'
Provides-Extra: lints
Requires-Dist: pyrsistent ; extra == 'lints'
Requires-Dist: ufmt ; extra == 'lints'
Requires-Dist: flake8 ; extra == 'lints'
Requires-Dist: mypy ; (implementation_name == "cpython") and extra == 'lints'
Provides-Extra: optional
Requires-Dist: pyrsistent ; extra == 'optional'
Provides-Extra: tests
Requires-Dist: pyrsistent ; extra == 'tests'
Requires-Dist: pytest ; extra == 'tests'
Requires-Dist: pytest-sugar ; extra == 'tests'
Requires-Dist: coverage ; extra == 'tests'
Requires-Dist: pytest-coverage ; extra == 'tests'
Requires-Dist: hypothesis ; extra == 'tests'
